pyromises/__init__.py
pyromises/promise/__init__.py
pyromises-0.0.2.dist-info/LICENSE
pyromises-0.0.2.dist-info/METADATA
pyromises-0.0.2.dist-info/WHEEL
pyromises-0.0.2.dist-info/top_level.txt
pyromises-0.0.2.dist-info/RECORD
