Metadata-Version: 2.1
Name: pyromises
Version: 0.0.2
Summary: Promises for Python
Home-page: UNKNOWN
Author: Eder Lima
Author-email: lima.eder101@gmail.com
License: MIT
Keywords: python,async,promises
Platform: UNKNOWN
